README.txt
setup.py
plone/__init__.py
plone.recipe.squid.egg-info/PKG-INFO
plone.recipe.squid.egg-info/SOURCES.txt
plone.recipe.squid.egg-info/dependency_links.txt
plone.recipe.squid.egg-info/entry_points.txt
plone.recipe.squid.egg-info/namespace_packages.txt
plone.recipe.squid.egg-info/not-zip-safe
plone.recipe.squid.egg-info/requires.txt
plone.recipe.squid.egg-info/top_level.txt
plone/recipe/__init__.py
plone/recipe/squid/__init__.py
plone/recipe/squid/iRedirector.py
plone/recipe/squid/redirector_class.py
plone/recipe/squid/template-vhm.conf
plone/recipe/squid/template.conf
