Metadata-Version: 1.0
Name: plone.recipe.squid
Version: 1.0b1
Summary: Buildout recipe to install squid
Home-page: UNKNOWN
Author: Ricardo Newbery
Author-email: ric@digitalmarbles.com
License: GPL
Keywords: buildout squid cache proxy
Platform: UNKNOWN
Classifier: Framework :: Buildout
Classifier: Framework :: Zope2
Classifier: Intended Audience :: System Administrators
Classifier: License :: OSI Approved :: GNU General Public License (GPL)
Classifier: Operating System :: POSIX
Classifier: Topic :: Internet :: Proxy Servers
